README.md
setup.py
automig/__init__.py
automig/__main__.py
automig/automig_sqlite.py
automig/migrate_pg.py
automig/version.py
automig.egg-info/PKG-INFO
automig.egg-info/SOURCES.txt
automig.egg-info/dependency_links.txt
automig.egg-info/entry_points.txt
automig.egg-info/requires.txt
automig.egg-info/top_level.txt
automig/lib/__init__.py
automig/lib/diffing.py
automig/lib/githelp.py
automig/lib/ref_diff.py
automig/lib/sa_harness.py
automig/lib/wrappers.py
test/test_diffing.py
test/test_git.py
test/test_harness.py