Metadata-Version: 2.1
Name: automig
Version: 0.1.5
Summary: Declarative, automatic db migrations using SQL & git as the source of truth
Home-page: https://github.com/abe-winter/automigrate
Author: Abe Winter
Author-email: awinter.public+automig@gmail.com
License: UNKNOWN
Keywords: sql,migration,git,diff
Platform: UNKNOWN
Requires-Python: >=3.6
Provides-Extra: postgres
